Akatosh/__init__.py
Akatosh/entity.py
Akatosh/event.py
Akatosh/resource.py
Akatosh/universe.py
akatosh-3.1.6.dist-info/LICENSE
akatosh-3.1.6.dist-info/METADATA
akatosh-3.1.6.dist-info/WHEEL
akatosh-3.1.6.dist-info/RECORD
