Metadata-Version: 2.1
Name: Akatosh
Version: 3.1.6
Summary: Discrete event simulation framework supports real-time simulation without time step!
Home-page: https://ulfaric.github.io/Akatosh/
License: CC-BY-NC-ND-4.0
Author: ulfaric
Author-email: ryf0510@live.com
Requires-Python: >=3.7,<4.0
Classifier: License :: Other/Proprietary License
Classifier: Programming Language :: Python :: 3
Classifier: Programming Language :: Python :: 3.7
Classifier: Programming Language :: Python :: 3.8
Classifier: Programming Language :: Python :: 3.9
Classifier: Programming Language :: Python :: 3.10
Classifier: Programming Language :: Python :: 3.11
Classifier: Programming Language :: Python :: 3.12
Requires-Dist: colorlog (>=6.8.2,<7.0.0)
Project-URL: Repository, https://github.com/ulfaric/Akatosh
